README.rst
distribute_setup.py
setup.py
chimpusers/__init__.py
chimpusers/admin.py
chimpusers/exceptions.py
chimpusers/forms.py
chimpusers/models.py
chimpusers/tests.py
chimpusers/utils.py
chimpusers/management/__init__.py
chimpusers/management/commands/__init__.py
chimpusers/management/commands/chimpsync.py
django_chimpusers.egg-info/PKG-INFO
django_chimpusers.egg-info/SOURCES.txt
django_chimpusers.egg-info/dependency_links.txt
django_chimpusers.egg-info/top_level.txt