Metadata-Version: 1.1
Name: django-chimpusers
Version: 0.1.8
Summary: Integrate Django users with a MailChimp mailing list.
Home-page: https://github.com/Quixotix/django-chimpusers
Author: Micah Carrick
Author-email: micah@quixotix.com
License: BSD
Platform: UNKNOWN
Classifier: Development Status :: 5 - Production/Stable
Classifier: Environment :: Web Environment
Classifier: Intended Audience :: Developers
Classifier: Operating System :: OS Independent
Classifier: Programming Language :: Python
Classifier: Topic :: Software Development :: Libraries :: Python Modules
Classifier: License :: OSI Approved :: BSD License
